cy_encrypt/__init__.py
cy_encrypt/cli.py
cy_encrypt/tools.py
cy_encrypt/version.py
tests/__init__.py
cy_encrypt-0.1.0.dist-info/LICENSE
cy_encrypt-0.1.0.dist-info/METADATA
cy_encrypt-0.1.0.dist-info/WHEEL
cy_encrypt-0.1.0.dist-info/top_level.txt
cy_encrypt-0.1.0.dist-info/RECORD
