Metadata-Version: 2.1
Name: cy_encrypt
Version: 0.1.0
Summary: Convert Python source code to a dynamic link library using Cython
Author: Max Cheung
Author-email: max@maxckm.com
License-File: LICENSE
Requires-Dist: Cython
Requires-Dist: click
